mdaencore/bootstrap.py
mdaencore/similarity.py
mdaencore/covariance.py
mdaencore/__init__.py
mdaencore/cutils.c
mdaencore/confdistmatrix.py
mdaencore/utils.py
mdaencore/cutils.pyx
mdaencore/cutils.cpython-311-darwin.so
mdaencore/tests/__init__.py
mdaencore/tests/test_mdaencore.py
mdaencore/clustering/affinityprop.pyx
mdaencore/clustering/affinityprop.c
mdaencore/clustering/ClusteringMethod.py
mdaencore/clustering/__init__.py
mdaencore/clustering/cluster.py
mdaencore/clustering/ClusterCollection.py
mdaencore/clustering/affinityprop.cpython-311-darwin.so
mdaencore/clustering/include/ap.h
mdaencore/clustering/src/ap.c
mdaencore/dimensionality_reduction/stochasticproxembed.c
mdaencore/dimensionality_reduction/stochasticproxembed.pyx
mdaencore/dimensionality_reduction/__init__.py
mdaencore/dimensionality_reduction/stochasticproxembed.cpython-311-darwin.so
mdaencore/dimensionality_reduction/DimensionalityReductionMethod.py
mdaencore/dimensionality_reduction/reduce_dimensionality.py
mdaencore/dimensionality_reduction/include/spe.h
mdaencore/dimensionality_reduction/src/spe.c
mdaencore-1.0.0.dist-info/AUTHORS.md
mdaencore-1.0.0.dist-info/RECORD
mdaencore-1.0.0.dist-info/LICENSE
mdaencore-1.0.0.dist-info/WHEEL
mdaencore-1.0.0.dist-info/top_level.txt
mdaencore-1.0.0.dist-info/METADATA
