Metadata-Version: 2.1
Name: mdaencore
Version: 1.0.0
Summary: Ensemble overlap comparison software for molecular data.
Author: mdaencore AUTHORS
Author-email: Matteo Tiberti <tiberti@cancer.dk>, Wouter Boomsma <wb@di.ku.dk>, Tone Bengtsen <tonebengsten@gmail.com>, "Ian M. Kenney" <ikenney@asu.edu>
Maintainer-email: Kristoffer Enøe Johansson <kristoffer.johansson@bio.ku.dk>, Kresten Lindorff-Larsen <lindorff@bio.ku.dk>
License:                     GNU GENERAL PUBLIC LICENSE
Project-URL: documentation, https://www.mdanalysis.org/mdaencore/
Project-URL: Issue tracker, https://github.com/MDAnalysis/mdaencore/issues
Project-URL: MDAKit registry, https://mdakits.mdanalysis.org/mdaencore.html
Project-URL: source, https://github.com/MDAnalysis/mdaencore
Keywords: molecular simulations
Classifier: Development Status :: 6 - Mature
Classifier: Environment :: Console
Classifier: Intended Audience :: Science/Research
Classifier: License :: OSI Approved :: GNU General Public License v2 or later (GPLv2+)
Classifier: Operating System :: MacOS :: MacOS X
Classifier: Operating System :: Microsoft :: Windows
Classifier: Operating System :: POSIX
Classifier: Programming Language :: C
Classifier: Programming Language :: Python
Classifier: Programming Language :: Python :: 3.9
Classifier: Programming Language :: Python :: 3.10
Classifier: Programming Language :: Python :: 3.11
Classifier: Topic :: Scientific/Engineering
Classifier: Topic :: Software Development :: Libraries :: Python Modules
Requires-Python: >=3.9
License-File: LICENSE
License-File: AUTHORS.md
Requires-Dist: MDAnalysis>=2.0.0
Provides-Extra: test
Requires-Dist: pytest>=6.0; extra == "test"
Requires-Dist: pytest-xdist>=2.5; extra == "test"
Requires-Dist: pytest-cov>=3.0; extra == "test"
Provides-Extra: doc
Requires-Dist: sphinx; extra == "doc"
Requires-Dist: mdanalysis_sphinx_theme; extra == "doc"
